parabject.py
foyndation/__init__.py
foyndation-15.dist-info/METADATA
foyndation-15.dist-info/WHEEL
foyndation-15.dist-info/top_level.txt
foyndation-15.dist-info/RECORD
