Metadata-Version: 2.1
Name: foyndation
Version: 15
Summary: Base library of foyono projects
Home-page: https://pypi.org/project/foyndation/
Author: foyono
Author-email: shrovis@foyono.com
